README
setup.py
geodjango_tigerline.egg-info/PKG-INFO
geodjango_tigerline.egg-info/SOURCES.txt
geodjango_tigerline.egg-info/dependency_links.txt
geodjango_tigerline.egg-info/not-zip-safe
geodjango_tigerline.egg-info/top_level.txt
tigerline/__init__.py
tigerline/admin.py
tigerline/models.py
tigerline/views.py
tigerline/management/__init__.py
tigerline/management/commands/__init__.py
tigerline/management/commands/load_counties.py
tigerline/management/commands/load_states.py
tigerline/management/commands/load_tigerline.py
tigerline/management/commands/load_zipcodes.py
tigerline/migrations/0001_initial.py
tigerline/migrations/__init__.py
tigerline/south_migrations/0001_initial.py
tigerline/south_migrations/0002_auto.py
tigerline/south_migrations/0003_auto.py
tigerline/south_migrations/__init__.py