Metadata-Version: 1.1
Name: geodjango-tigerline
Version: 1.0.1
Summary: A resuable app with the boilerplate necessary for getting TIGER/LINE data into a GeoDjango project.
Home-page: https://github.com/adamfast/geodjango-tigerline
Author: Adam Fast
Author-email: adamfast@gmail.com
License: BSD
Keywords: django geodjango tigerline
Platform: UNKNOWN
Classifier: Development Status :: 5 - Production/Stable
Classifier: Environment :: Web Environment
Classifier: Framework :: Django
Classifier: Intended Audience :: Developers
Classifier: License :: OSI Approved :: BSD License
Classifier: Operating System :: OS Independent
Classifier: Programming Language :: Python
Classifier: Programming Language :: Python :: 2
Classifier: Topic :: Internet :: WWW/HTTP
Classifier: Topic :: Software Development :: Libraries :: Python Modules
